[{"name":"昌元街道","value":11.8362},{"name":"昌洲街道","value":6.8291},{"name":"广顺街道","value":4.9388},{"name":"双河街道","value":4.9411},{"name":"安富街道","value":4.0268},{"name":"峰高街道","value":3.1859},{"name":"直升镇","value":1.275},{"name":"路孔镇","value":1.0626},{"name":"清江镇","value":0.9928},{"name":"仁义镇","value":3.8864},{"name":"河包镇","value":2.7597},{"name":"古昌镇","value":1.8327},{"name":"吴家镇","value":3.4549},{"name":"观胜镇","value":1.3103},{"name":"铜鼓镇","value":1.1222},{"name":"清流镇","value":0.9172},{"name":"盘龙镇","value":5.1177},{"name":"远觉镇","value":0.9629},{"name":"清升镇","value":1.3636},{"name":"荣隆镇","value":3.2983},{"name":"龙集镇","value":1.0111}]