[{"name":"华阳路街道","value":7.273},{"name":"江苏路街道","value":5.1883},{"name":"新华路街道","value":7.323},{"name":"周家桥街道","value":5.6628},{"name":"天山路街道","value":7.3757},{"name":"仙霞新村街道","value":8.4664},{"name":"虹桥街道","value":5.9551},{"name":"程家桥街道","value":2.4487},{"name":"北新泾街道","value":4.6865},{"name":"新泾镇","value":14.6776},{"name":"静安区","value":24.6788},{"name":"江宁路街道","value":7.5272},{"name":"石门二路街道","value":3.4288},{"name":"南京西路街道","value":3.6544},{"name":"静安寺街道","value":2.9173},{"name":"曹家渡街道","value":7.1511}]